spottyr_edge_runtime/__init__.py
spottyr_edge_runtime/output_handler.py
spottyr_edge_runtime/workflow.py
spottyr_edge_runtime-0.1.6.dist-info/METADATA
spottyr_edge_runtime-0.1.6.dist-info/WHEEL
spottyr_edge_runtime-0.1.6.dist-info/top_level.txt
spottyr_edge_runtime-0.1.6.dist-info/RECORD
