Metadata-Version: 2.4
Name: spottyr-edge-runtime
Version: 0.1.6
Summary: A Python package for running Spottyr workflow on edge devices.
Author-email: Kane Ma <maxioncloud@gmail.com>
Project-URL: Homepage, https://github.com/Good-Call/spottyr-edge-runtime
Project-URL: Bug Tracker, https://github.com/Good-Call/spottyr-edge-runtime/issues
Classifier: Development Status :: 3 - Alpha
Classifier: Intended Audience :: Developers
Classifier: License :: OSI Approved :: MIT License
Classifier: Operating System :: OS Independent
Classifier: Programming Language :: Python :: 3
Classifier: Programming Language :: Python :: 3.8
Classifier: Programming Language :: Python :: 3.9
Classifier: Programming Language :: Python :: 3.10
Classifier: Programming Language :: Python :: 3.11
Classifier: Programming Language :: Python :: 3.12
Requires-Python: >=3.8
Requires-Dist: Pillow>=9.0.0
Requires-Dist: numpy>=1.22.0
Requires-Dist: opencv-python>=4.8.0.74
Requires-Dist: onnxruntime>=1.12.0
